bert/__init__.py
bert/cli.py
bert/code.py
bert/engine.py
bert/logger.py
bert_cli-1.2.0.dist-info/licenses/LICENSE
bert_cli-1.2.0.dist-info/METADATA
bert_cli-1.2.0.dist-info/WHEEL
bert_cli-1.2.0.dist-info/entry_points.txt
bert_cli-1.2.0.dist-info/top_level.txt
bert_cli-1.2.0.dist-info/RECORD
