Metadata-Version: 2.4
Name: bert-cli
Version: 1.2.0
Summary: Bert — A CLI Framework dev tool for decoder transformer models.
Home-page: https://github.com/mnisperuza/bert-cli
Author: Matias Nisperuza
Author-email: Matias Nisperuza <mnisperuza1102@gmail.com>
License: Apache 2.0
Project-URL: Homepage, https://mnisperuza.github.io/bert-cli/
Project-URL: Documentation, https://github.com/mnisperuza/bert-cli#readme
Project-URL: Repository, https://github.com/mnisperuza/bert-cli
Project-URL: Issues, https://github.com/mnisperuza/bert-cli
Keywords: ai,assistant,llm,local,cli,qwen
Classifier: Development Status :: 5 - Production/Stable
Classifier: Environment :: Console
Classifier: Intended Audience :: Developers
Classifier: Intended Audience :: End Users/Desktop
Classifier: Operating System :: OS Independent
Classifier: Operating System :: Microsoft :: Windows
Classifier: Operating System :: POSIX :: Linux
Classifier: Operating System :: MacOS
Classifier: Programming Language :: Python :: 3
Classifier: Programming Language :: Python :: 3.8
Classifier: Programming Language :: Python :: 3.9
Classifier: Programming Language :: Python :: 3.10
Classifier: Programming Language :: Python :: 3.11
Classifier: Programming Language :: Python :: 3.12
Classifier: Topic :: Scientific/Engineering :: Artificial Intelligence
Requires-Python: >=3.8
License-File: LICENSE
Requires-Dist: torch>=2.1.0
Requires-Dist: transformers>=4.42.0
Requires-Dist: accelerate>=0.27.0
Requires-Dist: huggingface-hub>=0.20.0
Requires-Dist: hf_xet>=1.1.0
Requires-Dist: safetensors>=0.4.0
Requires-Dist: sentencepiece>=0.1.99
Requires-Dist: einops>=0.7.0
Requires-Dist: numpy<2.0.0,>=1.24.0
Requires-Dist: bitsandbytes>=0.43.0
Provides-Extra: linux
Requires-Dist: bitsandbytes>=0.43.0; extra == "linux"
Provides-Extra: perf
Requires-Dist: xformers>=0.0.25; extra == "perf"
Provides-Extra: full
Requires-Dist: bitsandbytes>=0.43.0; extra == "full"
Requires-Dist: xformers>=0.0.25; extra == "full"
Dynamic: author
Dynamic: home-page
Dynamic: license-file
Dynamic: requires-python
